thedns/__init__.py
thedns/_wanwang.py
thedns-2.0.10.dist-info/licenses/LICENSE
thedns-2.0.10.dist-info/METADATA
thedns-2.0.10.dist-info/WHEEL
thedns-2.0.10.dist-info/top_level.txt
thedns-2.0.10.dist-info/RECORD
