Metadata-Version: 2.4
Name: thedns
Version: 2.0.10
Summary: Identify your device with $system_id.[private,public].theca.cn
Home-page: https://devnull.cn
Author: Xizhen Du
Author-email: xizhendu@gmail.com
License-File: LICENSE
Requires-Dist: requests
Requires-Dist: theid
Dynamic: author
Dynamic: author-email
Dynamic: description
Dynamic: description-content-type
Dynamic: home-page
Dynamic: license-file
Dynamic: requires-dist
Dynamic: summary
